<?xml version="1.0" encoding="UTF-8"?>
<!DOCTYPE mapper PUBLIC "-//mybatis.org//DTD Mapper 3.0//EN" "http://mybatis.org/dtd/mybatis-3-mapper.dtd">
<mapper namespace="com.youlema.sales.mapper.TourLineMapper">
  <resultMap id="BaseResultMap" type="com.youlema.sales.mapper.meta.TourLine">
    <!--
      WARNING - @mbggenerated
      This element is automatically generated by MyBatis Generator, do not modify.
      This element was generated on Wed Jun 19 20:58:41 CST 2013.
    -->
    <id column="tour_Line_Id" jdbcType="BIGINT" property="tourLineId" />
    <result column="product_Main_Type_Id" jdbcType="BIGINT" property="productMainTypeId" />
    <result column="product_Minor_Type_Id" jdbcType="BIGINT" property="productMinorTypeId" />
    <result column="line_Code" jdbcType="VARCHAR" property="lineCode" />
    <result column="line_Name" jdbcType="VARCHAR" property="lineName" />
    <result column="line_Topic" jdbcType="VARCHAR" property="lineTopic" />
    <result column="line_Type" jdbcType="VARCHAR" property="lineType" />
    <result column="line_Brand" jdbcType="VARCHAR" property="lineBrand" />
    <result column="tour_Cards" jdbcType="VARCHAR" property="tourCards" />
    <result column="before_Days_Grant_Vista" jdbcType="INTEGER" property="beforeDaysGrantVista" />
    <result column="days_Night" jdbcType="INTEGER" property="daysNight" />
    <result column="days_During" jdbcType="INTEGER" property="daysDuring" />
    <result column="leave_City" jdbcType="VARCHAR" property="leaveCity" />
    <result column="leave_City_Traffic" jdbcType="VARCHAR" property="leaveCityTraffic" />
    <result column="return_City" jdbcType="VARCHAR" property="returnCity" />
    <result column="return_City_Traffic" jdbcType="VARCHAR" property="returnCityTraffic" />
    <result column="through_Citys" jdbcType="VARCHAR" property="throughCitys" />
    <result column="tour_Attractions" jdbcType="VARCHAR" property="tourAttractions" />
    <result column="key_Words" jdbcType="VARCHAR" property="keyWords" />
    <result column="design_Status" jdbcType="CHAR" property="designStatus" />
    <result column="gmt_Desing_Complete" jdbcType="TIMESTAMP" property="gmtDesingComplete" />
    <result column="is_Enable" jdbcType="DECIMAL" property="isEnable" />
    <result column="gmt_Create" jdbcType="TIMESTAMP" property="gmtCreate" />
    <result column="creator" jdbcType="VARCHAR" property="creator" />
    <result column="gmt_Modify" jdbcType="TIMESTAMP" property="gmtModify" />
    <result column="modifier" jdbcType="VARCHAR" property="modifier" />
    <result column="memo" jdbcType="VARCHAR" property="memo" />
    <result column="audit_Opinion" jdbcType="VARCHAR" property="auditOpinion" />
    <result column="audit_Status" jdbcType="VARCHAR" property="auditStatus" />
    <result column="target_Customers" jdbcType="VARCHAR" property="targetCustomers" />
    <result column="tour_Purpose" jdbcType="VARCHAR" property="tourPurpose" />
    <result column="is_Deleted" jdbcType="DECIMAL" property="isDeleted" />
    <result column="PV" jdbcType="DECIMAL" property="pv" />
    <result column="applicable_Type" jdbcType="VARCHAR" property="applicableType" />
  </resultMap>
  <resultMap extends="BaseResultMap" id="ResultMapWithBLOBs" type="com.youlema.sales.mapper.meta.TourLine">
    <!--
      WARNING - @mbggenerated
      This element is automatically generated by MyBatis Generator, do not modify.
      This element was generated on Wed Jun 19 20:58:41 CST 2013.
    -->
    <result column="tour_Highlights" jdbcType="LONGVARCHAR" property="tourHighlights" />
  </resultMap>
  <sql id="Example_Where_Clause">
    <!--
      WARNING - @mbggenerated
      This element is automatically generated by MyBatis Generator, do not modify.
      This element was generated on Wed Jun 19 20:58:41 CST 2013.
    -->
    <where>
      <foreach collection="oredCriteria" item="criteria" separator="or">
        <if test="criteria.valid">
          <trim prefix="(" prefixOverrides="and" suffix=")">
            <foreach collection="criteria.criteria" item="criterion">
              <choose>
                <when test="criterion.noValue">
                  and ${criterion.condition}
                </when>
                <when test="criterion.singleValue">
                  and ${criterion.condition} #{criterion.value}
                </when>
                <when test="criterion.betweenValue">
                  and ${criterion.condition} #{criterion.value} and #{criterion.secondValue}
                </when>
                <when test="criterion.listValue">
                  and ${criterion.condition}
                  <foreach close=")" collection="criterion.value" item="listItem" open="(" separator=",">
                    #{listItem}
                  </foreach>
                </when>
              </choose>
            </foreach>
          </trim>
        </if>
      </foreach>
    </where>
  </sql>
  <sql id="Update_By_Example_Where_Clause">
    <!--
      WARNING - @mbggenerated
      This element is automatically generated by MyBatis Generator, do not modify.
      This element was generated on Wed Jun 19 20:58:41 CST 2013.
    -->
    <where>
      <foreach collection="example.oredCriteria" item="criteria" separator="or">
        <if test="criteria.valid">
          <trim prefix="(" prefixOverrides="and" suffix=")">
            <foreach collection="criteria.criteria" item="criterion">
              <choose>
                <when test="criterion.noValue">
                  and ${criterion.condition}
                </when>
                <when test="criterion.singleValue">
                  and ${criterion.condition} #{criterion.value}
                </when>
                <when test="criterion.betweenValue">
                  and ${criterion.condition} #{criterion.value} and #{criterion.secondValue}
                </when>
                <when test="criterion.listValue">
                  and ${criterion.condition}
                  <foreach close=")" collection="criterion.value" item="listItem" open="(" separator=",">
                    #{listItem}
                  </foreach>
                </when>
              </choose>
            </foreach>
          </trim>
        </if>
      </foreach>
    </where>
  </sql>
  <sql id="Base_Column_List">
    <!--
      WARNING - @mbggenerated
      This element is automatically generated by MyBatis Generator, do not modify.
      This element was generated on Wed Jun 19 20:58:41 CST 2013.
    -->
    tour_Line_Id, product_Main_Type_Id, product_Minor_Type_Id, line_Code, line_Name, 
    line_Topic, line_Type, line_Brand, tour_Cards, before_Days_Grant_Vista, days_Night, 
    days_During, leave_City, leave_City_Traffic, return_City, return_City_Traffic, through_Citys, 
    tour_Attractions, key_Words, design_Status, gmt_Desing_Complete, is_Enable, gmt_Create, 
    creator, gmt_Modify, modifier, memo, audit_Opinion, audit_Status, target_Customers, 
    tour_Purpose, is_Deleted, PV, applicable_Type
  </sql>
  <sql id="Blob_Column_List">
    <!--
      WARNING - @mbggenerated
      This element is automatically generated by MyBatis Generator, do not modify.
      This element was generated on Wed Jun 19 20:58:41 CST 2013.
    -->
    tour_Highlights
  </sql>
  <select id="selectByExampleWithBLOBs" parameterType="com.youlema.sales.mapper.meta.TourLineExample" resultMap="ResultMapWithBLOBs">
    <!--
      WARNING - @mbggenerated
      This element is automatically generated by MyBatis Generator, do not modify.
      This element was generated on Wed Jun 19 20:58:41 CST 2013.
    -->
    select
    <if test="distinct">
      distinct
    </if>
    <include refid="Base_Column_List" />
    ,
    <include refid="Blob_Column_List" />
    from Tour_Line
    <if test="_parameter != null">
      <include refid="Example_Where_Clause" />
    </if>
    <if test="orderByClause != null">
      order by ${orderByClause}
    </if>
  </select>
  <select id="selectByExample" parameterType="com.youlema.sales.mapper.meta.TourLineExample" resultMap="BaseResultMap">
    <!--
      WARNING - @mbggenerated
      This element is automatically generated by MyBatis Generator, do not modify.
      This element was generated on Wed Jun 19 20:58:41 CST 2013.
    -->
    select
    <if test="distinct">
      distinct
    </if>
    <include refid="Base_Column_List" />
    from Tour_Line
    <if test="_parameter != null">
      <include refid="Example_Where_Clause" />
    </if>
    <if test="orderByClause != null">
      order by ${orderByClause}
    </if>
  </select>
  <select id="selectByPrimaryKey" parameterType="java.lang.Long" resultMap="ResultMapWithBLOBs">
    <!--
      WARNING - @mbggenerated
      This element is automatically generated by MyBatis Generator, do not modify.
      This element was generated on Wed Jun 19 20:58:41 CST 2013.
    -->
    select 
    <include refid="Base_Column_List" />
    ,
    <include refid="Blob_Column_List" />
    from Tour_Line
    where tour_Line_Id = #{tourLineId,jdbcType=BIGINT}
  </select>
  <delete id="deleteByPrimaryKey" parameterType="java.lang.Long">
    <!--
      WARNING - @mbggenerated
      This element is automatically generated by MyBatis Generator, do not modify.
      This element was generated on Wed Jun 19 20:58:41 CST 2013.
    -->
    delete from Tour_Line
    where tour_Line_Id = #{tourLineId,jdbcType=BIGINT}
  </delete>
  <delete id="deleteByExample" parameterType="com.youlema.sales.mapper.meta.TourLineExample">
    <!--
      WARNING - @mbggenerated
      This element is automatically generated by MyBatis Generator, do not modify.
      This element was generated on Wed Jun 19 20:58:41 CST 2013.
    -->
    delete from Tour_Line
    <if test="_parameter != null">
      <include refid="Example_Where_Clause" />
    </if>
  </delete>
  <insert id="insert" parameterType="com.youlema.sales.mapper.meta.TourLine">
    <!--
      WARNING - @mbggenerated
      This element is automatically generated by MyBatis Generator, do not modify.
      This element was generated on Wed Jun 19 20:58:41 CST 2013.
    -->
    insert into Tour_Line (tour_Line_Id, product_Main_Type_Id, product_Minor_Type_Id, 
      line_Code, line_Name, line_Topic, 
      line_Type, line_Brand, tour_Cards, 
      before_Days_Grant_Vista, days_Night, days_During, 
      leave_City, leave_City_Traffic, return_City, 
      return_City_Traffic, through_Citys, tour_Attractions, 
      key_Words, design_Status, gmt_Desing_Complete, 
      is_Enable, gmt_Create, creator, 
      gmt_Modify, modifier, memo, 
      audit_Opinion, audit_Status, target_Customers, 
      tour_Purpose, is_Deleted, PV, 
      applicable_Type, tour_Highlights)
    values (#{tourLineId,jdbcType=BIGINT}, #{productMainTypeId,jdbcType=BIGINT}, #{productMinorTypeId,jdbcType=BIGINT}, 
      #{lineCode,jdbcType=VARCHAR}, #{lineName,jdbcType=VARCHAR}, #{lineTopic,jdbcType=VARCHAR}, 
      #{lineType,jdbcType=VARCHAR}, #{lineBrand,jdbcType=VARCHAR}, #{tourCards,jdbcType=VARCHAR}, 
      #{beforeDaysGrantVista,jdbcType=INTEGER}, #{daysNight,jdbcType=INTEGER}, #{daysDuring,jdbcType=INTEGER}, 
      #{leaveCity,jdbcType=VARCHAR}, #{leaveCityTraffic,jdbcType=VARCHAR}, #{returnCity,jdbcType=VARCHAR}, 
      #{returnCityTraffic,jdbcType=VARCHAR}, #{throughCitys,jdbcType=VARCHAR}, #{tourAttractions,jdbcType=VARCHAR}, 
      #{keyWords,jdbcType=VARCHAR}, #{designStatus,jdbcType=CHAR}, #{gmtDesingComplete,jdbcType=TIMESTAMP}, 
      #{isEnable,jdbcType=DECIMAL}, #{gmtCreate,jdbcType=TIMESTAMP}, #{creator,jdbcType=VARCHAR}, 
      #{gmtModify,jdbcType=TIMESTAMP}, #{modifier,jdbcType=VARCHAR}, #{memo,jdbcType=VARCHAR}, 
      #{auditOpinion,jdbcType=VARCHAR}, #{auditStatus,jdbcType=VARCHAR}, #{targetCustomers,jdbcType=VARCHAR}, 
      #{tourPurpose,jdbcType=VARCHAR}, #{isDeleted,jdbcType=DECIMAL}, #{pv,jdbcType=DECIMAL}, 
      #{applicableType,jdbcType=VARCHAR}, #{tourHighlights,jdbcType=LONGVARCHAR})
  </insert>
  <insert id="insertSelective" parameterType="com.youlema.sales.mapper.meta.TourLine">
    <!--
      WARNING - @mbggenerated
      This element is automatically generated by MyBatis Generator, do not modify.
      This element was generated on Wed Jun 19 20:58:41 CST 2013.
    -->
    insert into Tour_Line
    <trim prefix="(" suffix=")" suffixOverrides=",">
      <if test="tourLineId != null">
        tour_Line_Id,
      </if>
      <if test="productMainTypeId != null">
        product_Main_Type_Id,
      </if>
      <if test="productMinorTypeId != null">
        product_Minor_Type_Id,
      </if>
      <if test="lineCode != null">
        line_Code,
      </if>
      <if test="lineName != null">
        line_Name,
      </if>
      <if test="lineTopic != null">
        line_Topic,
      </if>
      <if test="lineType != null">
        line_Type,
      </if>
      <if test="lineBrand != null">
        line_Brand,
      </if>
      <if test="tourCards != null">
        tour_Cards,
      </if>
      <if test="beforeDaysGrantVista != null">
        before_Days_Grant_Vista,
      </if>
      <if test="daysNight != null">
        days_Night,
      </if>
      <if test="daysDuring != null">
        days_During,
      </if>
      <if test="leaveCity != null">
        leave_City,
      </if>
      <if test="leaveCityTraffic != null">
        leave_City_Traffic,
      </if>
      <if test="returnCity != null">
        return_City,
      </if>
      <if test="returnCityTraffic != null">
        return_City_Traffic,
      </if>
      <if test="throughCitys != null">
        through_Citys,
      </if>
      <if test="tourAttractions != null">
        tour_Attractions,
      </if>
      <if test="keyWords != null">
        key_Words,
      </if>
      <if test="designStatus != null">
        design_Status,
      </if>
      <if test="gmtDesingComplete != null">
        gmt_Desing_Complete,
      </if>
      <if test="isEnable != null">
        is_Enable,
      </if>
      <if test="gmtCreate != null">
        gmt_Create,
      </if>
      <if test="creator != null">
        creator,
      </if>
      <if test="gmtModify != null">
        gmt_Modify,
      </if>
      <if test="modifier != null">
        modifier,
      </if>
      <if test="memo != null">
        memo,
      </if>
      <if test="auditOpinion != null">
        audit_Opinion,
      </if>
      <if test="auditStatus != null">
        audit_Status,
      </if>
      <if test="targetCustomers != null">
        target_Customers,
      </if>
      <if test="tourPurpose != null">
        tour_Purpose,
      </if>
      <if test="isDeleted != null">
        is_Deleted,
      </if>
      <if test="pv != null">
        PV,
      </if>
      <if test="applicableType != null">
        applicable_Type,
      </if>
      <if test="tourHighlights != null">
        tour_Highlights,
      </if>
    </trim>
    <trim prefix="values (" suffix=")" suffixOverrides=",">
      <if test="tourLineId != null">
        #{tourLineId,jdbcType=BIGINT},
      </if>
      <if test="productMainTypeId != null">
        #{productMainTypeId,jdbcType=BIGINT},
      </if>
      <if test="productMinorTypeId != null">
        #{productMinorTypeId,jdbcType=BIGINT},
      </if>
      <if test="lineCode != null">
        #{lineCode,jdbcType=VARCHAR},
      </if>
      <if test="lineName != null">
        #{lineName,jdbcType=VARCHAR},
      </if>
      <if test="lineTopic != null">
        #{lineTopic,jdbcType=VARCHAR},
      </if>
      <if test="lineType != null">
        #{lineType,jdbcType=VARCHAR},
      </if>
      <if test="lineBrand != null">
        #{lineBrand,jdbcType=VARCHAR},
      </if>
      <if test="tourCards != null">
        #{tourCards,jdbcType=VARCHAR},
      </if>
      <if test="beforeDaysGrantVista != null">
        #{beforeDaysGrantVista,jdbcType=INTEGER},
      </if>
      <if test="daysNight != null">
        #{daysNight,jdbcType=INTEGER},
      </if>
      <if test="daysDuring != null">
        #{daysDuring,jdbcType=INTEGER},
      </if>
      <if test="leaveCity != null">
        #{leaveCity,jdbcType=VARCHAR},
      </if>
      <if test="leaveCityTraffic != null">
        #{leaveCityTraffic,jdbcType=VARCHAR},
      </if>
      <if test="returnCity != null">
        #{returnCity,jdbcType=VARCHAR},
      </if>
      <if test="returnCityTraffic != null">
        #{returnCityTraffic,jdbcType=VARCHAR},
      </if>
      <if test="throughCitys != null">
        #{throughCitys,jdbcType=VARCHAR},
      </if>
      <if test="tourAttractions != null">
        #{tourAttractions,jdbcType=VARCHAR},
      </if>
      <if test="keyWords != null">
        #{keyWords,jdbcType=VARCHAR},
      </if>
      <if test="designStatus != null">
        #{designStatus,jdbcType=CHAR},
      </if>
      <if test="gmtDesingComplete != null">
        #{gmtDesingComplete,jdbcType=TIMESTAMP},
      </if>
      <if test="isEnable != null">
        #{isEnable,jdbcType=DECIMAL},
      </if>
      <if test="gmtCreate != null">
        #{gmtCreate,jdbcType=TIMESTAMP},
      </if>
      <if test="creator != null">
        #{creator,jdbcType=VARCHAR},
      </if>
      <if test="gmtModify != null">
        #{gmtModify,jdbcType=TIMESTAMP},
      </if>
      <if test="modifier != null">
        #{modifier,jdbcType=VARCHAR},
      </if>
      <if test="memo != null">
        #{memo,jdbcType=VARCHAR},
      </if>
      <if test="auditOpinion != null">
        #{auditOpinion,jdbcType=VARCHAR},
      </if>
      <if test="auditStatus != null">
        #{auditStatus,jdbcType=VARCHAR},
      </if>
      <if test="targetCustomers != null">
        #{targetCustomers,jdbcType=VARCHAR},
      </if>
      <if test="tourPurpose != null">
        #{tourPurpose,jdbcType=VARCHAR},
      </if>
      <if test="isDeleted != null">
        #{isDeleted,jdbcType=DECIMAL},
      </if>
      <if test="pv != null">
        #{pv,jdbcType=DECIMAL},
      </if>
      <if test="applicableType != null">
        #{applicableType,jdbcType=VARCHAR},
      </if>
      <if test="tourHighlights != null">
        #{tourHighlights,jdbcType=LONGVARCHAR},
      </if>
    </trim>
  </insert>
  <select id="countByExample" parameterType="com.youlema.sales.mapper.meta.TourLineExample" resultType="java.lang.Integer">
    <!--
      WARNING - @mbggenerated
      This element is automatically generated by MyBatis Generator, do not modify.
      This element was generated on Wed Jun 19 20:58:41 CST 2013.
    -->
    select count(*) from Tour_Line
    <if test="_parameter != null">
      <include refid="Example_Where_Clause" />
    </if>
  </select>
  <update id="updateByExampleSelective" parameterType="map">
    <!--
      WARNING - @mbggenerated
      This element is automatically generated by MyBatis Generator, do not modify.
      This element was generated on Wed Jun 19 20:58:41 CST 2013.
    -->
    update Tour_Line
    <set>
      <if test="record.tourLineId != null">
        tour_Line_Id = #{record.tourLineId,jdbcType=BIGINT},
      </if>
      <if test="record.productMainTypeId != null">
        product_Main_Type_Id = #{record.productMainTypeId,jdbcType=BIGINT},
      </if>
      <if test="record.productMinorTypeId != null">
        product_Minor_Type_Id = #{record.productMinorTypeId,jdbcType=BIGINT},
      </if>
      <if test="record.lineCode != null">
        line_Code = #{record.lineCode,jdbcType=VARCHAR},
      </if>
      <if test="record.lineName != null">
        line_Name = #{record.lineName,jdbcType=VARCHAR},
      </if>
      <if test="record.lineTopic != null">
        line_Topic = #{record.lineTopic,jdbcType=VARCHAR},
      </if>
      <if test="record.lineType != null">
        line_Type = #{record.lineType,jdbcType=VARCHAR},
      </if>
      <if test="record.lineBrand != null">
        line_Brand = #{record.lineBrand,jdbcType=VARCHAR},
      </if>
      <if test="record.tourCards != null">
        tour_Cards = #{record.tourCards,jdbcType=VARCHAR},
      </if>
      <if test="record.beforeDaysGrantVista != null">
        before_Days_Grant_Vista = #{record.beforeDaysGrantVista,jdbcType=INTEGER},
      </if>
      <if test="record.daysNight != null">
        days_Night = #{record.daysNight,jdbcType=INTEGER},
      </if>
      <if test="record.daysDuring != null">
        days_During = #{record.daysDuring,jdbcType=INTEGER},
      </if>
      <if test="record.leaveCity != null">
        leave_City = #{record.leaveCity,jdbcType=VARCHAR},
      </if>
      <if test="record.leaveCityTraffic != null">
        leave_City_Traffic = #{record.leaveCityTraffic,jdbcType=VARCHAR},
      </if>
      <if test="record.returnCity != null">
        return_City = #{record.returnCity,jdbcType=VARCHAR},
      </if>
      <if test="record.returnCityTraffic != null">
        return_City_Traffic = #{record.returnCityTraffic,jdbcType=VARCHAR},
      </if>
      <if test="record.throughCitys != null">
        through_Citys = #{record.throughCitys,jdbcType=VARCHAR},
      </if>
      <if test="record.tourAttractions != null">
        tour_Attractions = #{record.tourAttractions,jdbcType=VARCHAR},
      </if>
      <if test="record.keyWords != null">
        key_Words = #{record.keyWords,jdbcType=VARCHAR},
      </if>
      <if test="record.designStatus != null">
        design_Status = #{record.designStatus,jdbcType=CHAR},
      </if>
      <if test="record.gmtDesingComplete != null">
        gmt_Desing_Complete = #{record.gmtDesingComplete,jdbcType=TIMESTAMP},
      </if>
      <if test="record.isEnable != null">
        is_Enable = #{record.isEnable,jdbcType=DECIMAL},
      </if>
      <if test="record.gmtCreate != null">
        gmt_Create = #{record.gmtCreate,jdbcType=TIMESTAMP},
      </if>
      <if test="record.creator != null">
        creator = #{record.creator,jdbcType=VARCHAR},
      </if>
      <if test="record.gmtModify != null">
        gmt_Modify = #{record.gmtModify,jdbcType=TIMESTAMP},
      </if>
      <if test="record.modifier != null">
        modifier = #{record.modifier,jdbcType=VARCHAR},
      </if>
      <if test="record.memo != null">
        memo = #{record.memo,jdbcType=VARCHAR},
      </if>
      <if test="record.auditOpinion != null">
        audit_Opinion = #{record.auditOpinion,jdbcType=VARCHAR},
      </if>
      <if test="record.auditStatus != null">
        audit_Status = #{record.auditStatus,jdbcType=VARCHAR},
      </if>
      <if test="record.targetCustomers != null">
        target_Customers = #{record.targetCustomers,jdbcType=VARCHAR},
      </if>
      <if test="record.tourPurpose != null">
        tour_Purpose = #{record.tourPurpose,jdbcType=VARCHAR},
      </if>
      <if test="record.isDeleted != null">
        is_Deleted = #{record.isDeleted,jdbcType=DECIMAL},
      </if>
      <if test="record.pv != null">
        PV = #{record.pv,jdbcType=DECIMAL},
      </if>
      <if test="record.applicableType != null">
        applicable_Type = #{record.applicableType,jdbcType=VARCHAR},
      </if>
      <if test="record.tourHighlights != null">
        tour_Highlights = #{record.tourHighlights,jdbcType=LONGVARCHAR},
      </if>
    </set>
    <if test="_parameter != null">
      <include refid="Update_By_Example_Where_Clause" />
    </if>
  </update>
  <update id="updateByExampleWithBLOBs" parameterType="map">
    <!--
      WARNING - @mbggenerated
      This element is automatically generated by MyBatis Generator, do not modify.
      This element was generated on Wed Jun 19 20:58:41 CST 2013.
    -->
    update Tour_Line
    set tour_Line_Id = #{record.tourLineId,jdbcType=BIGINT},
      product_Main_Type_Id = #{record.productMainTypeId,jdbcType=BIGINT},
      product_Minor_Type_Id = #{record.productMinorTypeId,jdbcType=BIGINT},
      line_Code = #{record.lineCode,jdbcType=VARCHAR},
      line_Name = #{record.lineName,jdbcType=VARCHAR},
      line_Topic = #{record.lineTopic,jdbcType=VARCHAR},
      line_Type = #{record.lineType,jdbcType=VARCHAR},
      line_Brand = #{record.lineBrand,jdbcType=VARCHAR},
      tour_Cards = #{record.tourCards,jdbcType=VARCHAR},
      before_Days_Grant_Vista = #{record.beforeDaysGrantVista,jdbcType=INTEGER},
      days_Night = #{record.daysNight,jdbcType=INTEGER},
      days_During = #{record.daysDuring,jdbcType=INTEGER},
      leave_City = #{record.leaveCity,jdbcType=VARCHAR},
      leave_City_Traffic = #{record.leaveCityTraffic,jdbcType=VARCHAR},
      return_City = #{record.returnCity,jdbcType=VARCHAR},
      return_City_Traffic = #{record.returnCityTraffic,jdbcType=VARCHAR},
      through_Citys = #{record.throughCitys,jdbcType=VARCHAR},
      tour_Attractions = #{record.tourAttractions,jdbcType=VARCHAR},
      key_Words = #{record.keyWords,jdbcType=VARCHAR},
      design_Status = #{record.designStatus,jdbcType=CHAR},
      gmt_Desing_Complete = #{record.gmtDesingComplete,jdbcType=TIMESTAMP},
      is_Enable = #{record.isEnable,jdbcType=DECIMAL},
      gmt_Create = #{record.gmtCreate,jdbcType=TIMESTAMP},
      creator = #{record.creator,jdbcType=VARCHAR},
      gmt_Modify = #{record.gmtModify,jdbcType=TIMESTAMP},
      modifier = #{record.modifier,jdbcType=VARCHAR},
      memo = #{record.memo,jdbcType=VARCHAR},
      audit_Opinion = #{record.auditOpinion,jdbcType=VARCHAR},
      audit_Status = #{record.auditStatus,jdbcType=VARCHAR},
      target_Customers = #{record.targetCustomers,jdbcType=VARCHAR},
      tour_Purpose = #{record.tourPurpose,jdbcType=VARCHAR},
      is_Deleted = #{record.isDeleted,jdbcType=DECIMAL},
      PV = #{record.pv,jdbcType=DECIMAL},
      applicable_Type = #{record.applicableType,jdbcType=VARCHAR},
      tour_Highlights = #{record.tourHighlights,jdbcType=LONGVARCHAR}
    <if test="_parameter != null">
      <include refid="Update_By_Example_Where_Clause" />
    </if>
  </update>
  <update id="updateByExample" parameterType="map">
    <!--
      WARNING - @mbggenerated
      This element is automatically generated by MyBatis Generator, do not modify.
      This element was generated on Wed Jun 19 20:58:41 CST 2013.
    -->
    update Tour_Line
    set tour_Line_Id = #{record.tourLineId,jdbcType=BIGINT},
      product_Main_Type_Id = #{record.productMainTypeId,jdbcType=BIGINT},
      product_Minor_Type_Id = #{record.productMinorTypeId,jdbcType=BIGINT},
      line_Code = #{record.lineCode,jdbcType=VARCHAR},
      line_Name = #{record.lineName,jdbcType=VARCHAR},
      line_Topic = #{record.lineTopic,jdbcType=VARCHAR},
      line_Type = #{record.lineType,jdbcType=VARCHAR},
      line_Brand = #{record.lineBrand,jdbcType=VARCHAR},
      tour_Cards = #{record.tourCards,jdbcType=VARCHAR},
      before_Days_Grant_Vista = #{record.beforeDaysGrantVista,jdbcType=INTEGER},
      days_Night = #{record.daysNight,jdbcType=INTEGER},
      days_During = #{record.daysDuring,jdbcType=INTEGER},
      leave_City = #{record.leaveCity,jdbcType=VARCHAR},
      leave_City_Traffic = #{record.leaveCityTraffic,jdbcType=VARCHAR},
      return_City = #{record.returnCity,jdbcType=VARCHAR},
      return_City_Traffic = #{record.returnCityTraffic,jdbcType=VARCHAR},
      through_Citys = #{record.throughCitys,jdbcType=VARCHAR},
      tour_Attractions = #{record.tourAttractions,jdbcType=VARCHAR},
      key_Words = #{record.keyWords,jdbcType=VARCHAR},
      design_Status = #{record.designStatus,jdbcType=CHAR},
      gmt_Desing_Complete = #{record.gmtDesingComplete,jdbcType=TIMESTAMP},
      is_Enable = #{record.isEnable,jdbcType=DECIMAL},
      gmt_Create = #{record.gmtCreate,jdbcType=TIMESTAMP},
      creator = #{record.creator,jdbcType=VARCHAR},
      gmt_Modify = #{record.gmtModify,jdbcType=TIMESTAMP},
      modifier = #{record.modifier,jdbcType=VARCHAR},
      memo = #{record.memo,jdbcType=VARCHAR},
      audit_Opinion = #{record.auditOpinion,jdbcType=VARCHAR},
      audit_Status = #{record.auditStatus,jdbcType=VARCHAR},
      target_Customers = #{record.targetCustomers,jdbcType=VARCHAR},
      tour_Purpose = #{record.tourPurpose,jdbcType=VARCHAR},
      is_Deleted = #{record.isDeleted,jdbcType=DECIMAL},
      PV = #{record.pv,jdbcType=DECIMAL},
      applicable_Type = #{record.applicableType,jdbcType=VARCHAR}
    <if test="_parameter != null">
      <include refid="Update_By_Example_Where_Clause" />
    </if>
  </update>
  <update id="updateByPrimaryKeySelective" parameterType="com.youlema.sales.mapper.meta.TourLine">
    <!--
      WARNING - @mbggenerated
      This element is automatically generated by MyBatis Generator, do not modify.
      This element was generated on Wed Jun 19 20:58:41 CST 2013.
    -->
    update Tour_Line
    <set>
      <if test="productMainTypeId != null">
        product_Main_Type_Id = #{productMainTypeId,jdbcType=BIGINT},
      </if>
      <if test="productMinorTypeId != null">
        product_Minor_Type_Id = #{productMinorTypeId,jdbcType=BIGINT},
      </if>
      <if test="lineCode != null">
        line_Code = #{lineCode,jdbcType=VARCHAR},
      </if>
      <if test="lineName != null">
        line_Name = #{lineName,jdbcType=VARCHAR},
      </if>
      <if test="lineTopic != null">
        line_Topic = #{lineTopic,jdbcType=VARCHAR},
      </if>
      <if test="lineType != null">
        line_Type = #{lineType,jdbcType=VARCHAR},
      </if>
      <if test="lineBrand != null">
        line_Brand = #{lineBrand,jdbcType=VARCHAR},
      </if>
      <if test="tourCards != null">
        tour_Cards = #{tourCards,jdbcType=VARCHAR},
      </if>
      <if test="beforeDaysGrantVista != null">
        before_Days_Grant_Vista = #{beforeDaysGrantVista,jdbcType=INTEGER},
      </if>
      <if test="daysNight != null">
        days_Night = #{daysNight,jdbcType=INTEGER},
      </if>
      <if test="daysDuring != null">
        days_During = #{daysDuring,jdbcType=INTEGER},
      </if>
      <if test="leaveCity != null">
        leave_City = #{leaveCity,jdbcType=VARCHAR},
      </if>
      <if test="leaveCityTraffic != null">
        leave_City_Traffic = #{leaveCityTraffic,jdbcType=VARCHAR},
      </if>
      <if test="returnCity != null">
        return_City = #{returnCity,jdbcType=VARCHAR},
      </if>
      <if test="returnCityTraffic != null">
        return_City_Traffic = #{returnCityTraffic,jdbcType=VARCHAR},
      </if>
      <if test="throughCitys != null">
        through_Citys = #{throughCitys,jdbcType=VARCHAR},
      </if>
      <if test="tourAttractions != null">
        tour_Attractions = #{tourAttractions,jdbcType=VARCHAR},
      </if>
      <if test="keyWords != null">
        key_Words = #{keyWords,jdbcType=VARCHAR},
      </if>
      <if test="designStatus != null">
        design_Status = #{designStatus,jdbcType=CHAR},
      </if>
      <if test="gmtDesingComplete != null">
        gmt_Desing_Complete = #{gmtDesingComplete,jdbcType=TIMESTAMP},
      </if>
      <if test="isEnable != null">
        is_Enable = #{isEnable,jdbcType=DECIMAL},
      </if>
      <if test="gmtCreate != null">
        gmt_Create = #{gmtCreate,jdbcType=TIMESTAMP},
      </if>
      <if test="creator != null">
        creator = #{creator,jdbcType=VARCHAR},
      </if>
      <if test="gmtModify != null">
        gmt_Modify = #{gmtModify,jdbcType=TIMESTAMP},
      </if>
      <if test="modifier != null">
        modifier = #{modifier,jdbcType=VARCHAR},
      </if>
      <if test="memo != null">
        memo = #{memo,jdbcType=VARCHAR},
      </if>
      <if test="auditOpinion != null">
        audit_Opinion = #{auditOpinion,jdbcType=VARCHAR},
      </if>
      <if test="auditStatus != null">
        audit_Status = #{auditStatus,jdbcType=VARCHAR},
      </if>
      <if test="targetCustomers != null">
        target_Customers = #{targetCustomers,jdbcType=VARCHAR},
      </if>
      <if test="tourPurpose != null">
        tour_Purpose = #{tourPurpose,jdbcType=VARCHAR},
      </if>
      <if test="isDeleted != null">
        is_Deleted = #{isDeleted,jdbcType=DECIMAL},
      </if>
      <if test="pv != null">
        PV = #{pv,jdbcType=DECIMAL},
      </if>
      <if test="applicableType != null">
        applicable_Type = #{applicableType,jdbcType=VARCHAR},
      </if>
      <if test="tourHighlights != null">
        tour_Highlights = #{tourHighlights,jdbcType=LONGVARCHAR},
      </if>
    </set>
    where tour_Line_Id = #{tourLineId,jdbcType=BIGINT}
  </update>
  <update id="updateByPrimaryKeyWithBLOBs" parameterType="com.youlema.sales.mapper.meta.TourLine">
    <!--
      WARNING - @mbggenerated
      This element is automatically generated by MyBatis Generator, do not modify.
      This element was generated on Wed Jun 19 20:58:41 CST 2013.
    -->
    update Tour_Line
    set product_Main_Type_Id = #{productMainTypeId,jdbcType=BIGINT},
      product_Minor_Type_Id = #{productMinorTypeId,jdbcType=BIGINT},
      line_Code = #{lineCode,jdbcType=VARCHAR},
      line_Name = #{lineName,jdbcType=VARCHAR},
      line_Topic = #{lineTopic,jdbcType=VARCHAR},
      line_Type = #{lineType,jdbcType=VARCHAR},
      line_Brand = #{lineBrand,jdbcType=VARCHAR},
      tour_Cards = #{tourCards,jdbcType=VARCHAR},
      before_Days_Grant_Vista = #{beforeDaysGrantVista,jdbcType=INTEGER},
      days_Night = #{daysNight,jdbcType=INTEGER},
      days_During = #{daysDuring,jdbcType=INTEGER},
      leave_City = #{leaveCity,jdbcType=VARCHAR},
      leave_City_Traffic = #{leaveCityTraffic,jdbcType=VARCHAR},
      return_City = #{returnCity,jdbcType=VARCHAR},
      return_City_Traffic = #{returnCityTraffic,jdbcType=VARCHAR},
      through_Citys = #{throughCitys,jdbcType=VARCHAR},
      tour_Attractions = #{tourAttractions,jdbcType=VARCHAR},
      key_Words = #{keyWords,jdbcType=VARCHAR},
      design_Status = #{designStatus,jdbcType=CHAR},
      gmt_Desing_Complete = #{gmtDesingComplete,jdbcType=TIMESTAMP},
      is_Enable = #{isEnable,jdbcType=DECIMAL},
      gmt_Create = #{gmtCreate,jdbcType=TIMESTAMP},
      creator = #{creator,jdbcType=VARCHAR},
      gmt_Modify = #{gmtModify,jdbcType=TIMESTAMP},
      modifier = #{modifier,jdbcType=VARCHAR},
      memo = #{memo,jdbcType=VARCHAR},
      audit_Opinion = #{auditOpinion,jdbcType=VARCHAR},
      audit_Status = #{auditStatus,jdbcType=VARCHAR},
      target_Customers = #{targetCustomers,jdbcType=VARCHAR},
      tour_Purpose = #{tourPurpose,jdbcType=VARCHAR},
      is_Deleted = #{isDeleted,jdbcType=DECIMAL},
      PV = #{pv,jdbcType=DECIMAL},
      applicable_Type = #{applicableType,jdbcType=VARCHAR},
      tour_Highlights = #{tourHighlights,jdbcType=LONGVARCHAR}
    where tour_Line_Id = #{tourLineId,jdbcType=BIGINT}
  </update>
  <update id="updateByPrimaryKey" parameterType="com.youlema.sales.mapper.meta.TourLine">
    <!--
      WARNING - @mbggenerated
      This element is automatically generated by MyBatis Generator, do not modify.
      This element was generated on Wed Jun 19 20:58:41 CST 2013.
    -->
    update Tour_Line
    set product_Main_Type_Id = #{productMainTypeId,jdbcType=BIGINT},
      product_Minor_Type_Id = #{productMinorTypeId,jdbcType=BIGINT},
      line_Code = #{lineCode,jdbcType=VARCHAR},
      line_Name = #{lineName,jdbcType=VARCHAR},
      line_Topic = #{lineTopic,jdbcType=VARCHAR},
      line_Type = #{lineType,jdbcType=VARCHAR},
      line_Brand = #{lineBrand,jdbcType=VARCHAR},
      tour_Cards = #{tourCards,jdbcType=VARCHAR},
      before_Days_Grant_Vista = #{beforeDaysGrantVista,jdbcType=INTEGER},
      days_Night = #{daysNight,jdbcType=INTEGER},
      days_During = #{daysDuring,jdbcType=INTEGER},
      leave_City = #{leaveCity,jdbcType=VARCHAR},
      leave_City_Traffic = #{leaveCityTraffic,jdbcType=VARCHAR},
      return_City = #{returnCity,jdbcType=VARCHAR},
      return_City_Traffic = #{returnCityTraffic,jdbcType=VARCHAR},
      through_Citys = #{throughCitys,jdbcType=VARCHAR},
      tour_Attractions = #{tourAttractions,jdbcType=VARCHAR},
      key_Words = #{keyWords,jdbcType=VARCHAR},
      design_Status = #{designStatus,jdbcType=CHAR},
      gmt_Desing_Complete = #{gmtDesingComplete,jdbcType=TIMESTAMP},
      is_Enable = #{isEnable,jdbcType=DECIMAL},
      gmt_Create = #{gmtCreate,jdbcType=TIMESTAMP},
      creator = #{creator,jdbcType=VARCHAR},
      gmt_Modify = #{gmtModify,jdbcType=TIMESTAMP},
      modifier = #{modifier,jdbcType=VARCHAR},
      memo = #{memo,jdbcType=VARCHAR},
      audit_Opinion = #{auditOpinion,jdbcType=VARCHAR},
      audit_Status = #{auditStatus,jdbcType=VARCHAR},
      target_Customers = #{targetCustomers,jdbcType=VARCHAR},
      tour_Purpose = #{tourPurpose,jdbcType=VARCHAR},
      is_Deleted = #{isDeleted,jdbcType=DECIMAL},
      PV = #{pv,jdbcType=DECIMAL},
      applicable_Type = #{applicableType,jdbcType=VARCHAR}
    where tour_Line_Id = #{tourLineId,jdbcType=BIGINT}
  </update>
</mapper>